tunesynctool/__init__.py
tunesynctool/cli/__init__.py
tunesynctool/cli/main.py
tunesynctool/cli/commands/__init__.py
tunesynctool/cli/commands/sync.py
tunesynctool/cli/commands/transfer.py
tunesynctool/cli/utils/driver.py
tunesynctool/drivers/__init__.py
tunesynctool/drivers/service_driver.py
tunesynctool/drivers/service_mapper.py
tunesynctool/drivers/common/__init__.py
tunesynctool/drivers/common/deezer/__init__.py
tunesynctool/drivers/common/deezer/driver.py
tunesynctool/drivers/common/deezer/mapper.py
tunesynctool/drivers/common/spotify/__init__.py
tunesynctool/drivers/common/spotify/driver.py
tunesynctool/drivers/common/spotify/mapper.py
tunesynctool/drivers/common/subsonic/__init__.py
tunesynctool/drivers/common/subsonic/driver.py
tunesynctool/drivers/common/subsonic/mapper.py
tunesynctool/drivers/common/youtube/__init__.py
tunesynctool/drivers/common/youtube/driver.py
tunesynctool/drivers/common/youtube/mapper.py
tunesynctool/exceptions/__init__.py
tunesynctool/features/__init__.py
tunesynctool/features/playlist_sync.py
tunesynctool/features/track_matcher.py
tunesynctool/integrations/__init__.py
tunesynctool/integrations/musicbrainz.py
tunesynctool/models/__init__.py
tunesynctool/models/configuration.py
tunesynctool/models/playlist.py
tunesynctool/models/track.py
tunesynctool/utilities/__init__.py
tunesynctool/utilities/collections.py
tunesynctool/utilities/comparison.py
tunesynctool/utilities/normalization.py
tunesynctool-1.2.1.dist-info/LICENSE
tunesynctool-1.2.1.dist-info/METADATA
tunesynctool-1.2.1.dist-info/WHEEL
tunesynctool-1.2.1.dist-info/entry_points.txt
tunesynctool-1.2.1.dist-info/top_level.txt
tunesynctool-1.2.1.dist-info/RECORD
