Metadata-Version: 2.2
Name: tunesynctool
Version: 1.2.1
Summary: A package and CLI tool to build scripts that interact with various music streaming services.
Author-email: WilliamNT <wntbox@gmail.com>
Project-URL: Homepage, https://github.com/WilliamNT/tunesynctool
Project-URL: Issues, https://github.com/WilliamNT/tunesynctool/issues
Project-URL: Documentation, https://github.com/WilliamNT/tunesynctool/wiki
Classifier: Development Status :: 5 - Production/Stable
Classifier: Programming Language :: Python :: 3
Classifier: Operating System :: OS Independent
Classifier: Environment :: Console
Classifier: Intended Audience :: Developers
License-File: LICENSE
Requires-Dist: spotipy
Requires-Dist: py-sonic
Requires-Dist: musicbrainzngs
Requires-Dist: thefuzz
Requires-Dist: streamrip
Requires-Dist: ytmusicapi
Requires-Dist: click
Requires-Dist: tqdm
Requires-Dist: importlib-metadata; python_version < "3.11"
